aspen_jinja2_renderer.py
aspen_jinja2-0.5.dist-info/DESCRIPTION.rst
aspen_jinja2-0.5.dist-info/METADATA
aspen_jinja2-0.5.dist-info/RECORD
aspen_jinja2-0.5.dist-info/WHEEL
aspen_jinja2-0.5.dist-info/entry_points.txt
aspen_jinja2-0.5.dist-info/metadata.json
aspen_jinja2-0.5.dist-info/top_level.txt
