Metadata-Version: 2.0
Name: aspen-jinja2
Version: 0.5
Summary: jinja2 plugin for Aspen
Home-page: http://aspen.io/
Author: Chad Whitacre
Author-email: chad@zetaweb.com
License: UNKNOWN
Platform: UNKNOWN
Classifier: Development Status :: 4 - Beta
Classifier: Environment :: Console
Classifier: Intended Audience :: Developers
Classifier: License :: OSI Approved :: MIT License
Classifier: Natural Language :: English
Classifier: Operating System :: MacOS :: MacOS X
Classifier: Operating System :: Microsoft :: Windows
Classifier: Operating System :: POSIX
Classifier: Programming Language :: Python :: 2.6
Classifier: Programming Language :: Python :: 2.7
Classifier: Programming Language :: Python :: Implementation :: CPython
Classifier: Programming Language :: Python :: Implementation :: Jython
Classifier: Topic :: Internet :: WWW/HTTP :: HTTP Servers
Requires-Dist: aspen (>=0.37)
Requires-Dist: jinja2
